benzinga/__init__.py
benzinga/benzinga_errors.py
benzinga/config.py
benzinga/financial_data.py
benzinga/news_data.py
benzinga/param_check.py
benzinga-1.21.dist-info/METADATA
benzinga-1.21.dist-info/RECORD
benzinga-1.21.dist-info/WHEEL
benzinga-1.21.dist-info/top_level.txt
