Metadata-Version: 2.1
Name: benzinga
Version: 1.21
Summary: Python Client Library for Benzinga Data
Home-page: https://github.com/Benzinga/benzinga-python-client
Author: Benzinga Developers
Author-email: dev@benzinga.com
License: UNKNOWN
Platform: UNKNOWN
Classifier: Programming Language :: Python :: 3
Classifier: License :: OSI Approved :: MIT License
Classifier: Operating System :: OS Independent
Requires-Dist: requests
Requires-Dist: structlog
Requires-Dist: urllib3 (==1.25.10)
